<Ui xmlns='http://www.blizzard.com/wow/ui/'>
	<Button name='ElvUIAuraTemplate' inherits='ElvUIAuraIconTemplate' virtual='true' framelevel='4' registerForClicks='RightButtonUp, RightButtonDown'></Button> <!-- framelevel 4 for Masque support -->

	<Script file='Shared\General\Initialize.lua'/>

	<Script file='..\Locales\enUS.lua'/>
	<Script file='..\Locales\deDE.lua'/>
	<Script file='..\Locales\esMX.lua'/>
	<Script file='..\Locales\esES.lua'/>
	<Script file='..\Locales\frFR.lua'/>
	<Script file='..\Locales\itIT.lua'/>
	<Script file='..\Locales\koKR.lua'/>
	<Script file='..\Locales\ptBR.lua'/>
	<Script file='..\Locales\ruRU.lua'/>
	<Script file='..\Locales\trTR.lua'/>
	<Script file='..\Locales\zhTW.lua'/>
	<Script file='..\Locales\zhCN.lua'/>

	<Script file='Shared\Developer\Test.lua'/>
	<Script file='Shared\Developer\Frame.lua'/>
	<Script file='Shared\Developer\TInspect.lua'/>
	<Script file='Shared\Media\SharedMedia.lua'/>
	<Include file ='Shared\Modules\load_fonts.xml'/> <!-- Dynamic Fonts -->
	<Script file='Shared\Defaults\Profile.lua'/>
	<Script file='Shared\Defaults\Global.lua'/>
	<Script file='Shared\Defaults\Private.lua'/>
	<Include file ='Shared\Modules\load_templates.xml'/> <!-- ElvUIStaticPopupTemplate -->
	<Script file='Shared\General\Core.lua'/>
	<Script file='Shared\General\Math.lua'/>
	<Script file='Shared\General\API.lua'/>
	<Script file='Shared\General\Fonts.lua'/>
	<Script file='Shared\General\Install.lua'/>
	<Script file='Shared\General\PluginInstaller.lua'/>
	<Script file='Shared\General\PixelPerfect.lua'/>
	<Script file='Shared\General\Toolkit.lua'/>
	<Script file='Shared\General\StatusReport.lua'/>
	<Script file='Shared\General\Commands.lua'/>
	<Script file='Shared\General\StaticPopups.lua'/>
	<Script file='Shared\General\Animation.lua'/>
	<Script file='Shared\General\Smoothie.lua'/>
	<Script file='Shared\General\Movers.lua'/>
	<Script file='Shared\General\Config.lua'/>
	<Script file='Shared\General\Tutorials.lua'/>
	<Script file='Shared\General\Distributor.lua'/>
	<Script file='Shared\General\Dropdown.lua'/>
	<Script file='Shared\General\ItemLevel.lua'/>
	<Script file='Shared\General\Cooldowns.lua'/>
	<Script file='Shared\General\MapInfo.lua'/>
	<Script file='Shared\General\ModuleCopy.lua'/>
	<Script file='Shared\Tags\API.lua'/>
	<Script file='Shared\Tags\Tags.lua'/>
	<Script file='Shared\Layout\Layout.lua'/>
	<Include file='Shared\Modules\load_modules.xml'/>
	<Script file='Shared\Filters\Filters.lua'/>

	<Script file='TBC\Filters\Filters.lua'/>
	<Script file='TBC\Blizzard\ColorPicker.lua'/>
	<Script file='Shared\Modules\Blizzard\QuestWatch.lua'/>
	<Script file='Shared\Modules\DataTexts\Ammo.lua'/>
	<Script file='Shared\Modules\DataTexts\Avoidance.lua'/>
	<Script file='Shared\Modules\DataTexts\Block.lua'/>
	<Script file='Shared\Modules\DataTexts\Defense.lua'/>
	<Script file='Shared\Modules\DataTexts\Dodge.lua'/>
	<Script file='Shared\Modules\DataTexts\DualSpec.lua'/>
	<Script file='Shared\Modules\DataTexts\EnergyRegen.lua'/>
	<Script file='Shared\Modules\DataTexts\HealPower.lua'/>
	<Script file='Shared\Modules\DataTexts\Hit.lua'/>
	<Script file='Shared\Modules\DataTexts\Parry.lua'/>
	<Script file='Shared\Modules\DataTexts\SpellCrit.lua'/>
	<Script file='Shared\Modules\DataTexts\SpellHit.lua'/>
	<Script file='Shared\Modules\DataTexts\SpellPower.lua'/>
	<Script file='Shared\Modules\DataTexts\Spirit.lua'/>
	<Script file='Shared\Modules\DataBars\PetExperience.lua'/>
	<Script file='TBC\Skins\AddonManager.lua'/>
	<Script file='TBC\Skins\AuctionHouse.lua'/>
	<Script file='TBC\Skins\Bags.lua'/>
	<Script file='TBC\Skins\Battlefield.lua'/>
	<Script file='TBC\Skins\Battlenet.lua'/>
	<Script file='TBC\Skins\BGMap.lua'/>
	<Script file='TBC\Skins\BGScore.lua'/>
	<Script file='TBC\Skins\BlizzardOptions.lua'/>
	<Script file='TBC\Skins\Channels.lua'/>
	<Script file='TBC\Skins\Character.lua'/>
	<Script file='TBC\Skins\Communities.lua'/>
	<Script file='TBC\Skins\Craft.lua'/>
	<Script file='TBC\Skins\Debug.lua'/>
	<Script file='TBC\Skins\DressingRoom.lua'/>
	<Script file='TBC\Skins\EditorManager.lua'/>
	<Script file='TBC\Skins\EventTrace.lua'/>
	<Script file='TBC\Skins\Friends.lua'/>
	<Script file='TBC\Skins\GMChat.lua'/>
	<Script file='TBC\Skins\Gossip.lua'/>
	<Script file='TBC\Skins\GuildBank.lua'/>
	<Script file='TBC\Skins\GuildControl.lua'/>
	<Script file='TBC\Skins\GuildRegistrar.lua'/>
	<Script file='TBC\Skins\Help.lua'/>
	<Script file='TBC\Skins\Inspect.lua'/>
	<Script file='TBC\Skins\LFG.lua'/>
	<Script file='TBC\Skins\Loot.lua'/>
	<Script file='TBC\Skins\Macro.lua'/>
	<Script file='TBC\Skins\Mail.lua'/>
	<Script file='TBC\Skins\Menu.lua'/>
	<Script file='TBC\Skins\Merchant.lua'/>
	<Script file='TBC\Skins\MirrorTimers.lua'/>
	<Script file='TBC\Skins\Misc.lua'/>
	<Script file='TBC\Skins\NonRaid.lua'/>
	<Script file='TBC\Skins\Petition.lua'/>
	<Script file='TBC\Skins\Quest.lua'/>
	<Script file='TBC\Skins\QuestTimers.lua'/>
	<Script file='TBC\Skins\Raid.lua'/>
	<Script file='TBC\Skins\SettingsPanel.lua'/>
	<Script file='TBC\Skins\Socket.lua'/>
	<Script file='TBC\Skins\SpellBook.lua'/>
	<Script file='TBC\Skins\Stable.lua'/>
	<Script file='TBC\Skins\Tabard.lua'/>
	<Script file='TBC\Skins\Talent.lua'/>
	<Script file='TBC\Skins\Taxi.lua'/>
	<Script file='TBC\Skins\TimeManager.lua'/>
	<Script file='TBC\Skins\Tooltip.lua'/>
	<Script file='TBC\Skins\Trade.lua'/>
	<Script file='TBC\Skins\TradeSkill.lua'/>
	<Script file='TBC\Skins\Trainer.lua'/>
	<Script file='TBC\Skins\Tutorial.lua'/>
	<Script file='TBC\Skins\WorldMap.lua'/>
</Ui>
